ofxstatement_be_keytrade-0.0.1-py3.7-nspkg.pth
ofxstatement/plugins/keytrade.py
ofxstatement_be_keytrade-0.0.1.dist-info/METADATA
ofxstatement_be_keytrade-0.0.1.dist-info/WHEEL
ofxstatement_be_keytrade-0.0.1.dist-info/entry_points.txt
ofxstatement_be_keytrade-0.0.1.dist-info/namespace_packages.txt
ofxstatement_be_keytrade-0.0.1.dist-info/top_level.txt
ofxstatement_be_keytrade-0.0.1.dist-info/zip-safe
ofxstatement_be_keytrade-0.0.1.dist-info/RECORD
