Metadata-Version: 2.1
Name: ofxstatement-be-keytrade
Version: 0.0.1
Summary: OFXStatement plugin for KeytradeBank (Belgium)
Home-page: UNKNOWN
Author: Serkan Eryilmaz
Author-email: s.eryilmaz@scotchy.be
License: GPLv3
Keywords: ofx,banking,statement
Platform: UNKNOWN
Classifier: Development Status :: 3 - Alpha
Classifier: Programming Language :: Python :: 3
Classifier: Natural Language :: English
Classifier: Topic :: Office/Business :: Financial :: Accounting
Classifier: Topic :: Utilities
Classifier: Environment :: Console
Classifier: Operating System :: OS Independent
Classifier: License :: OSI Approved :: GNU Affero General Public License v3
Requires-Dist: ofxstatement
